bop
largeblue
bebop
