Metadata-Version: 1.0
Name: largeblue.order
Version: 0.2
Summary: An adapter to make containers and their contents orderable
Home-page: http://pesto.largeblue.net/trac/browser/largeblue/devel/largeblue.order
Author: James Arthur
Author-email: firstname.lastname@largeblue.com
License: Public Domain (note, vendor code contained within has own licenses)
Keywords: zope largeblue order ordering reorder orderable container bebop
Platform: UNKNOWN
Classifier: Programming Language :: Python
Classifier: Environment :: Web Environment
Classifier: Topic :: Internet :: WWW/HTTP :: WSGI :: Application
Classifier: Framework :: Zope3
Classifier: Intended Audience :: Developers
Classifier: License :: Public Domain
Classifier: Natural Language :: English
